{
  "resourceType": "Bundle",
  "id": "OpConsultRecord-0bb6c3c9-71f2-4ad6-ba14-edc20d5536d1",
  "meta": {
    "versionId": "0",
    "lastUpdated": "2024-05-31T22:10:13.049+05:30",
    "profile": [ "https://nrces.in/ndhm/fhir/r4/StructureDefinition/DocumentBundle" ]
  },
  "identifier": {
    "system": "http://hip.in",
    "value": "OpConsultRecord-0bb6c3c9-71f2-4ad6-ba14-edc20d5536d1"
  },
  "type": "document",
  "timestamp": "2024-05-31T22:10:13.049+05:30",
  "entry": [ {
    "fullUrl": "Composition/c4eb13af-082c-4b86-9e4b-0776582d42b6",
    "resource": {
      "resourceType": "Composition",
      "id": "c4eb13af-082c-4b86-9e4b-0776582d42b6",
      "meta": {
        "versionId": "0",
        "lastUpdated": "2024-05-31T22:10:13.049+05:30",
        "profile": [ "https://nrces.in/ndhm/fhir/r4/StructureDefinition/OPConsultRecord" ]
      },
      "language": "en-IN",
      "identifier": {
        "system": "https://ndhm.in/phr",
        "value": "c4eb13af-082c-4b86-9e4b-0776582d42b6"
      },
      "status": "final",
      "type": {
        "coding": [ {
          "system": "http://snomed.info/sct",
          "code": "371530004",
          "display": "Clinical consultation report"
        } ],
        "text": "Clinical consultation report"
      },
      "subject": {
        "reference": "Patient/5f6bfd47-49c2-4423-a38b-5731af7d94cb"
      },
      "date": "2024-05-31T22:10:13+05:30",
      "title": "OP Consultation Record",
      "section": [ {
        "title": "Medical History",
        "code": {
          "coding": [ {
            "system": "http://snomed.info/sct",
            "code": "422843007",
            "display": "Medical History Section"
          } ],
          "text": "Medical History Section"
        },
        "entry": [ {
          "reference": "Condition/07af9c6a-cb96-4ca7-9b5e-9e01700b4a2a"
        }, {
          "reference": "DiagnosticReport/c3c9388e-9e98-4ddf-96f8-45e3a39b0abb"
        }, {
          "reference": "DiagnosticReport/ca0e015a-1e90-4158-8050-49a49491d712"
        }, {
          "reference": "DiagnosticReport/b5943dfb-a4e3-4ff1-b047-0231849f0679"
        }, {
          "reference": "DiagnosticReport/026a40dd-bccd-4a2c-9e91-019cd699ee1d"
        }, {
          "reference": "DiagnosticReport/cf782f77-00e6-4609-a62b-5422fe74f32f"
        }, {
          "reference": "DiagnosticReport/271d5201-77cc-4523-b0de-c4b1d3733e26"
        }, {
          "reference": "DiagnosticReport/b0e46fbc-f0f0-4a0d-be29-ab995b130141"
        }, {
          "reference": "DiagnosticReport/9f140b11-f514-46eb-87f7-e4678510e865"
        }, {
          "reference": "DiagnosticReport/fd16f2ed-8f54-4684-a2c7-5090267770ca"
        } ]
      }, {
        "title": "Medical History",
        "code": {
          "coding": [ {
            "system": "http://snomed.info/sct",
            "code": "422843007",
            "display": "Medical History Section"
          } ],
          "text": "Medical History Section"
        },
        "entry": [ {
          "reference": "Condition/114c216b-b5f3-4a71-a7d2-43a7b91017d1"
        }, {
          "reference": "DiagnosticReport/d06004fa-cd8e-47b9-ae67-da4f15bcce18"
        }, {
          "reference": "DiagnosticReport/e1e1bd99-b622-44c2-8045-a6b728cca7f9"
        } ]
      }, {
        "title": "Drug Allergy Section",
        "code": {
          "coding": [ {
            "system": "http://snomed.info/sct",
            "code": "235719002",
            "display": "Drug Allergy Section"
          } ],
          "text": "Drug Allergy Section"
        },
        "entry": [ {
          "reference": "AllergyIntolerance/b3ab3f1a-61ec-43c5-8c96-fa7eaaec019c"
        } ]
      }, {
        "title": "Drug Allergy Section",
        "code": {
          "coding": [ {
            "system": "http://snomed.info/sct",
            "code": "235719002",
            "display": "Drug Allergy Section"
          } ],
          "text": "Drug Allergy Section"
        },
        "entry": [ {
          "reference": "AllergyIntolerance/fc382d86-0f7d-477b-a793-0280bd2c718a"
        } ]
      }, {
        "title": "Co-Morbidities",
        "code": {
          "coding": [ {
            "system": "http://snomed.info/sct",
            "code": "38341003",
            "display": "hypertension"
          } ]
        },
        "entry": [ {
          "reference": "Condition/ee2ac5a0-7486-45b4-b81d-4eadc083fde3"
        } ]
      }, {
        "title": "Co-Morbidities",
        "code": {
          "coding": [ {
            "system": "http://snomed.info/sct",
            "code": "53741008",
            "display": "Coronary Artery Disease"
          } ]
        },
        "entry": [ {
          "reference": "Condition/0f58b677-6825-4835-91a3-8dfe04b3d4c4"
        } ]
      }, {
        "title": "Adverse Events",
        "entry": [ {
          "reference": "AdverseEvent/03f38c75-8b22-4348-bae3-abedebf41c9d"
        } ]
      }, {
        "title": "Past Medical History",
        "code": {
          "coding": [ {
            "system": "http://snomed.info/sct",
            "code": "38341003",
            "display": "hypertension"
          } ]
        },
        "entry": [ {
          "reference": "Condition/ad1c7d3a-c960-4128-9995-d12ca53da231"
        } ]
      }, {
        "title": "Past Medical History",
        "code": {
          "coding": [ {
            "system": "http://snomed.info/sct",
            "code": "53741008",
            "display": "Coronary Artery Disease"
          } ]
        },
        "entry": [ {
          "reference": "Condition/58ea0dc5-b0aa-4195-8376-8cc6c7339617"
        } ]
      }, {
        "title": "Past Surgical History",
        "code": {
          "coding": [ {
            "system": "http://snomed.info/sct",
            "code": "38341003",
            "display": "hypertension"
          } ]
        },
        "entry": [ {
          "reference": "Condition/7e349876-9ed3-4b80-a492-3f5ea60d18ff"
        } ]
      }, {
        "title": "Past Surgical History",
        "code": {
          "coding": [ {
            "system": "http://snomed.info/sct",
            "code": "hypertension",
            "display": "Past Surgical History Section"
          } ],
          "text": "Past Surgical History Section"
        }
      }, {
        "title": "Past Surgical History",
        "code": {
          "coding": [ {
            "system": "http://snomed.info/sct",
            "code": "53741008",
            "display": "Coronary Artery Disease"
          } ]
        },
        "entry": [ {
          "reference": "Condition/25488d23-801a-452c-92e6-3952c2daef55"
        } ]
      }, {
        "title": "Mental Health Assesment",
        "code": {
          "coding": [ {
            "system": "http://loinc.org",
            "code": "82810-3",
            "display": "Pregnancy status"
          } ],
          "text": "Pregnancy status"
        },
        "entry": [ {
          "reference": "Observation/0f442276-e2d7-40ba-aa68-a50403a32f80"
        } ]
      }, {
        "title": "Mental Health Assesment",
        "code": {
          "coding": [ {
            "system": "http://loinc.org",
            "code": "Pregnancy status",
            "display": "Mental Health Assesment Section"
          } ],
          "text": "Mental Health Assesment Section"
        }
      }, {
        "title": "Mental Health Assesment",
        "code": {
          "coding": [ {
            "system": "http://loinc.org",
            "code": "83318-7",
            "display": "Menstrual cycle"
          } ],
          "text": "Menstrual cycle"
        },
        "entry": [ {
          "reference": "Observation/a6b864da-e41d-45f1-b9a2-b910e521676b"
        } ]
      }, {
        "title": "Menstruation History",
        "code": {
          "coding": [ {
            "system": "http://loinc.org",
            "code": "82810-3",
            "display": "Pregnancy status"
          } ],
          "text": "Pregnancy status"
        },
        "entry": [ {
          "reference": "Observation/cf93b34d-a34d-44b1-8c88-4ab2c0c1c6dd"
        } ]
      }, {
        "title": "Menstruation History",
        "code": {
          "coding": [ {
            "system": "http://loinc.org",
            "code": "83318-7",
            "display": "Menstrual cycle"
          } ],
          "text": "Menstrual cycle"
        },
        "entry": [ {
          "reference": "Observation/76e065d1-4942-43f3-825d-b2779d2e1880"
        } ]
      }, {
        "title": "Menstruation History",
        "code": {
          "coding": [ {
            "system": "http://loinc.org",
            "code": "Menstrual cycle",
            "display": "Menstruation History Section"
          } ],
          "text": "Menstruation History Section"
        }
      }, {
        "title": "Investigation Advice",
        "code": {
          "coding": [ {
            "system": "http://loinc.org",
            "code": "10187-3",
            "display": "obstetric history"
          } ],
          "text": "obstetric history"
        },
        "entry": [ {
          "reference": "ServiceRequest/748d3321-3ca4-4118-ac9f-91436f7406f4"
        } ]
      }, {
        "title": "Investigation Advice",
        "code": {
          "coding": [ {
            "system": "http://loinc.org",
            "code": "10193-1",
            "display": "breast health"
          } ],
          "text": "breast health"
        },
        "entry": [ {
          "reference": "ServiceRequest/f70b7a52-32f5-4b78-88f9-930da707cc85"
        } ]
      }, {
        "title": "Investigation Advice",
        "code": {
          "coding": [ {
            "system": "http://snomed.info/sct",
            "code": "306206005",
            "display": "Investigation Advice Section"
          } ],
          "text": "Investigation Advice Section"
        }
      }, {
        "title": "Surgical Summary With Post OP Course",
        "entry": [ {
          "reference": "Procedure/ff8cfa0d-5922-45aa-b864-14a631ac72b8"
        } ]
      }, {
        "title": "Surgical Summary With Post OP Course",
        "entry": [ {
          "reference": "Procedure/376f0c08-049a-4330-a248-eac0f5fe484c"
        } ]
      }, {
        "title": "Ongoing Drugs",
        "entry": [ {
          "reference": "MedicationStatement/ca0a2345-89f8-4688-af43-f3bb4e485907"
        } ]
      }, {
        "title": "Ongoing Drugs",
        "entry": [ {
          "reference": "MedicationStatement/8c797e26-705a-4e55-8394-58dbb59cef7c"
        } ]
      }, {
        "title": "Ongoing Drugs",
        "code": {
          "coding": [ {
            "system": "http://snomed.info/sct",
            "code": "385633008",
            "display": "Ongoing Drugs Section"
          } ],
          "text": "Ongoing Drugs Section"
        }
      } ]
    }
  }, {
    "fullUrl": "Observation/b2d5f567-264b-4878-a546-20b85813b920",
    "resource": {
      "resourceType": "Observation",
      "id": "b2d5f567-264b-4878-a546-20b85813b920",
      "code": {
        "coding": [ {
          "system": "http://loinc.org",
          "code": "8302-2",
          "display": "Body Height"
        } ]
      },
      "subject": {
        "reference": "Patient/Testing"
      },
      "valueCodeableConcept": {
        "coding": [ {
          "system": "http://snomed.info/sct",
          "code": "50373000",
          "display": "160.0"
        } ],
        "text": "Height"
      }
    }
  }, {
    "fullUrl": "Observation/da882854-69e4-4af7-9761-cf06b8e47f95",
    "resource": {
      "resourceType": "Observation",
      "id": "da882854-69e4-4af7-9761-cf06b8e47f95",
      "code": {
        "coding": [ {
          "system": "http://loinc.org",
          "code": "29463-7",
          "display": "Body Weight"
        } ]
      },
      "subject": {
        "reference": "Patient/Testing"
      },
      "valueCodeableConcept": {
        "coding": [ {
          "system": "http://snomed.info/sct",
          "code": "27113001",
          "display": "62.0"
        } ],
        "text": "Weight"
      }
    }
  }, {
    "fullUrl": "Observation/45803ae1-019f-4686-96a0-30bd316cfb05",
    "resource": {
      "resourceType": "Observation",
      "id": "45803ae1-019f-4686-96a0-30bd316cfb05",
      "code": {
        "coding": [ {
          "system": "http://loinc.org",
          "code": "39156-5",
          "display": "Body mass index (BMI)"
        } ]
      },
      "subject": {
        "reference": "Patient/Testing"
      },
      "valueCodeableConcept": {
        "coding": [ {
          "system": "http://snomed.info/sct",
          "code": "60621009",
          "display": "62.499999999999986"
        } ],
        "text": "Body mass index (BMI)"
      }
    }
  }, {
    "fullUrl": "Observation/170a3b8e-9b84-42d4-b5a9-8aceddde6cc9",
    "resource": {
      "resourceType": "Observation",
      "id": "170a3b8e-9b84-42d4-b5a9-8aceddde6cc9",
      "code": {
        "coding": [ {
          "system": "http://loinc.org",
          "code": "882-1",
          "display": "Blood group"
        } ]
      },
      "valueCodeableConcept": {
        "coding": [ {
          "system": "http://snomed.info/sct",
          "code": "365637002",
          "display": "A+"
        } ],
        "text": "A+"
      }
    }
  }, {
    "fullUrl": "Patient/5f6bfd47-49c2-4423-a38b-5731af7d94cb",
    "resource": {
      "resourceType": "Patient",
      "id": "5f6bfd47-49c2-4423-a38b-5731af7d94cb",
      "meta": {
        "versionId": "0",
        "lastUpdated": "2024-05-31T22:10:13.053+05:30",
        "profile": [ "https://nrces.in/ndhm/fhir/r4/StructureDefinition/Patient" ]
      },
      "identifier": [ {
        "type": {
          "coding": [ {
            "system": "http://terminology.hl7.org/CodeSystem/v2-0203",
            "code": "MR",
            "display": "Medical record number"
          } ],
          "text": "Medical record number"
        },
        "system": "NCG",
        "value": "123"
      } ],
      "name": [ {
        "text": "Testing POC 1",
        "given": [ "Testing POC" ]
      } ],
      "gender": "male",
      "birthDate": "1999-08-14",
      "address": [ {
        "type": "both",
        "text": "House Name: 123",
        "city": "Mrj",
        "district": "xyz",
        "state": "UP",
        "postalCode": "123456",
        "country": "India"
      } ]
    }
  }, {
    "fullUrl": "Condition/07af9c6a-cb96-4ca7-9b5e-9e01700b4a2a",
    "resource": {
      "resourceType": "Condition",
      "id": "07af9c6a-cb96-4ca7-9b5e-9e01700b4a2a",
      "meta": {
        "versionId": "0",
        "lastUpdated": "2024-05-31T22:10:13.054+05:30",
        "profile": [ "https://nrces.in/ndhm/fhir/r4/StructureDefinition/Condition" ]
      },
      "clinicalStatus": {
        "coding": [ {
          "system": "http://terminology.hl7.org/CodeSystem/condition-clinical",
          "code": "active",
          "display": "active"
        } ],
        "text": "Active"
      },
      "code": {
        "coding": [ {
          "system": "http://loinc.org",
          "code": "LOINC:59015-0",
          "display": "Lung Cancer"
        } ],
        "text": "Lung Cancer"
      }
    }
  }, {
    "fullUrl": "DiagnosticReport/c3c9388e-9e98-4ddf-96f8-45e3a39b0abb",
    "resource": {
      "resourceType": "DiagnosticReport",
      "id": "c3c9388e-9e98-4ddf-96f8-45e3a39b0abb",
      "status": "final",
      "code": {
        "coding": [ {
          "system": "http://loinc.org",
          "code": "LOINC:24590-2",
          "display": "MRI brain"
        } ],
        "text": "MRI brain"
      },
      "subject": {
        "reference": "Patient/5f6bfd47-49c2-4423-a38b-5731af7d94cb"
      },
      "issued": "2024-05-31T22:10:13.054+05:30",
      "result": [ {
        "reference": "DocumentReference/19c50729-7fbf-4f9d-b701-8655a289247c"
      } ]
    }
  }, {
    "fullUrl": "DocumentReference/19c50729-7fbf-4f9d-b701-8655a289247c",
    "resource": {
      "resourceType": "DocumentReference",
      "id": "19c50729-7fbf-4f9d-b701-8655a289247c",
      "status": "current",
      "type": {
        "coding": [ {
          "system": "http://loinc.org",
          "code": "LOINC:24590-2",
          "display": "MRI brain report"
        } ],
        "text": "MRI brain report"
      },
      "subject": {
        "reference": "Patient/5f6bfd47-49c2-4423-a38b-5731af7d94cb"
      },
      "content": [ {
        "attachment": {
          "contentType": "application/pdf",
          "data": "bHVuZ21yaQ==",
          "title": "MRI brain report"
        }
      } ]
    }
  }, {
    "fullUrl": "DiagnosticReport/ca0e015a-1e90-4158-8050-49a49491d712",
    "resource": {
      "resourceType": "DiagnosticReport",
      "id": "ca0e015a-1e90-4158-8050-49a49491d712",
      "status": "final",
      "code": {
        "coding": [ {
          "system": "http://loinc.org",
          "code": "LOINC:100231-0",
          "display": "Endobronchial ultrasound with ROSE reports"
        } ],
        "text": "Endobronchial ultrasound with ROSE reports"
      },
      "subject": {
        "reference": "Patient/5f6bfd47-49c2-4423-a38b-5731af7d94cb"
      },
      "issued": "2024-05-31T22:10:13.056+05:30",
      "result": [ {
        "reference": "DocumentReference/8fc15806-504f-4df8-8f31-dba053451d9a"
      } ]
    }
  }, {
    "fullUrl": "DocumentReference/8fc15806-504f-4df8-8f31-dba053451d9a",
    "resource": {
      "resourceType": "DocumentReference",
      "id": "8fc15806-504f-4df8-8f31-dba053451d9a",
      "status": "current",
      "type": {
        "coding": [ {
          "system": "http://loinc.org",
          "code": "LOINC:100231-0",
          "display": "Endobronchial ultrasound with ROSE reports report"
        } ],
        "text": "Endobronchial ultrasound with ROSE reports report"
      },
      "subject": {
        "reference": "Patient/5f6bfd47-49c2-4423-a38b-5731af7d94cb"
      },
      "content": [ {
        "attachment": {
          "contentType": "application/pdf",
          "data": "bHVuZ2VuZG8=",
          "title": "Endobronchial ultrasound with ROSE reports report"
        }
      } ]
    }
  }, {
    "fullUrl": "DiagnosticReport/b5943dfb-a4e3-4ff1-b047-0231849f0679",
    "resource": {
      "resourceType": "DiagnosticReport",
      "id": "b5943dfb-a4e3-4ff1-b047-0231849f0679",
      "status": "final",
      "code": {
        "coding": [ {
          "system": "http://loinc.org",
          "code": "LOINC:18744-3",
          "display": "Fiber optic bronchoscopy"
        } ],
        "text": "Fiber optic bronchoscopy"
      },
      "subject": {
        "reference": "Patient/5f6bfd47-49c2-4423-a38b-5731af7d94cb"
      },
      "issued": "2024-05-31T22:10:13.056+05:30",
      "result": [ {
        "reference": "DocumentReference/e970cdbe-ab57-4a5c-b3b6-5bf665deb6a9"
      } ]
    }
  }, {
    "fullUrl": "DocumentReference/e970cdbe-ab57-4a5c-b3b6-5bf665deb6a9",
    "resource": {
      "resourceType": "DocumentReference",
      "id": "e970cdbe-ab57-4a5c-b3b6-5bf665deb6a9",
      "status": "current",
      "type": {
        "coding": [ {
          "system": "http://loinc.org",
          "code": "LOINC:18744-3",
          "display": "Fiber optic bronchoscopy report"
        } ],
        "text": "Fiber optic bronchoscopy report"
      },
      "subject": {
        "reference": "Patient/5f6bfd47-49c2-4423-a38b-5731af7d94cb"
      },
      "content": [ {
        "attachment": {
          "contentType": "application/pdf",
          "data": "bHVuZ2ZpYnJl",
          "title": "Fiber optic bronchoscopy report"
        }
      } ]
    }
  }, {
    "fullUrl": "DiagnosticReport/026a40dd-bccd-4a2c-9e91-019cd699ee1d",
    "resource": {
      "resourceType": "DiagnosticReport",
      "id": "026a40dd-bccd-4a2c-9e91-019cd699ee1d",
      "status": "final",
      "code": {
        "coding": [ {
          "system": "http://loinc.org",
          "code": "LOINC:34552-0",
          "display": "2 D ECHO with PASP"
        } ],
        "text": "2 D ECHO with PASP"
      },
      "subject": {
        "reference": "Patient/5f6bfd47-49c2-4423-a38b-5731af7d94cb"
      },
      "issued": "2024-05-31T22:10:13.057+05:30",
      "result": [ {
        "reference": "DocumentReference/c8dbe9a6-bbf2-4bc4-a42c-8abc7d22c975"
      } ]
    }
  }, {
    "fullUrl": "DocumentReference/c8dbe9a6-bbf2-4bc4-a42c-8abc7d22c975",
    "resource": {
      "resourceType": "DocumentReference",
      "id": "c8dbe9a6-bbf2-4bc4-a42c-8abc7d22c975",
      "status": "current",
      "type": {
        "coding": [ {
          "system": "http://loinc.org",
          "code": "LOINC:34552-0",
          "display": "2 D ECHO with PASP report"
        } ],
        "text": "2 D ECHO with PASP report"
      },
      "subject": {
        "reference": "Patient/5f6bfd47-49c2-4423-a38b-5731af7d94cb"
      },
      "content": [ {
        "attachment": {
          "contentType": "application/pdf",
          "data": "bHVuZzJk",
          "title": "2 D ECHO with PASP report"
        }
      } ]
    }
  }, {
    "fullUrl": "DiagnosticReport/cf782f77-00e6-4609-a62b-5422fe74f32f",
    "resource": {
      "resourceType": "DiagnosticReport",
      "id": "cf782f77-00e6-4609-a62b-5422fe74f32f",
      "status": "final",
      "code": {
        "coding": [ {
          "system": "http://loinc.org",
          "code": "LOINC:81553-0",
          "display": "FDG PETCT"
        } ],
        "text": "FDG PETCT"
      },
      "subject": {
        "reference": "Patient/5f6bfd47-49c2-4423-a38b-5731af7d94cb",
        "display": "Testing POC"
      },
      "issued": "2024-05-31T22:10:13.058+05:30",
      "result": [ {
        "reference": "DocumentReference/0cdd252e-1eff-4a7f-ac22-34b2f14eca5a"
      } ]
    }
  }, {
    "fullUrl": "DocumentReference/0cdd252e-1eff-4a7f-ac22-34b2f14eca5a",
    "resource": {
      "resourceType": "DocumentReference",
      "id": "0cdd252e-1eff-4a7f-ac22-34b2f14eca5a",
      "status": "current",
      "type": {
        "coding": [ {
          "system": "http://loinc.org",
          "code": "LOINC:81553-0",
          "display": "FDG PETCT report"
        } ],
        "text": "FDG PETCT report"
      },
      "subject": {
        "reference": "Patient/5f6bfd47-49c2-4423-a38b-5731af7d94cb"
      },
      "content": [ {
        "attachment": {
          "contentType": "application/pdf",
          "data": "bHVuZ2ZkZg==",
          "title": "FDG PETCT report"
        }
      } ]
    }
  }, {
    "fullUrl": "DiagnosticReport/271d5201-77cc-4523-b0de-c4b1d3733e26",
    "resource": {
      "resourceType": "DiagnosticReport",
      "id": "271d5201-77cc-4523-b0de-c4b1d3733e26",
      "status": "final",
      "code": {
        "coding": [ {
          "system": "http://loinc.org",
          "code": "LOINC:58477-1",
          "display": "Pulmonary function tests with DLCO"
        } ],
        "text": "Pulmonary function tests with DLCO"
      },
      "subject": {
        "reference": "Patient/5f6bfd47-49c2-4423-a38b-5731af7d94cb"
      },
      "issued": "2024-05-31T22:10:13.059+05:30",
      "result": [ {
        "reference": "DocumentReference/f548802f-9fac-45a3-85ba-52f905fc9e71"
      } ]
    }
  }, {
    "fullUrl": "DocumentReference/f548802f-9fac-45a3-85ba-52f905fc9e71",
    "resource": {
      "resourceType": "DocumentReference",
      "id": "f548802f-9fac-45a3-85ba-52f905fc9e71",
      "status": "current",
      "type": {
        "coding": [ {
          "system": "http://loinc.org",
          "code": "LOINC:58477-1",
          "display": "Pulmonary function tests with DLCO report"
        } ],
        "text": "Pulmonary function tests with DLCO report"
      },
      "subject": {
        "reference": "Patient/5f6bfd47-49c2-4423-a38b-5731af7d94cb"
      },
      "content": [ {
        "attachment": {
          "contentType": "application/pdf",
          "data": "bHVuZ3B1bG1vbmFyeQ==",
          "title": "Pulmonary function tests with DLCO report"
        }
      } ]
    }
  }, {
    "fullUrl": "DiagnosticReport/b0e46fbc-f0f0-4a0d-be29-ab995b130141",
    "resource": {
      "resourceType": "DiagnosticReport",
      "id": "b0e46fbc-f0f0-4a0d-be29-ab995b130141",
      "status": "final",
      "code": {
        "coding": [ {
          "system": "http://loinc.org",
          "code": "LOINC:39942-8",
          "display": "V/Q scan in pneumonectomy"
        } ],
        "text": "V/Q scan in pneumonectomy"
      },
      "subject": {
        "reference": "Patient/5f6bfd47-49c2-4423-a38b-5731af7d94cb",
        "display": "Testing POC"
      },
      "issued": "2024-05-31T22:10:13.059+05:30",
      "result": [ {
        "reference": "DocumentReference/6acfe544-df75-4d2a-9d47-a5661f43f18f"
      } ]
    }
  }, {
    "fullUrl": "DocumentReference/6acfe544-df75-4d2a-9d47-a5661f43f18f",
    "resource": {
      "resourceType": "DocumentReference",
      "id": "6acfe544-df75-4d2a-9d47-a5661f43f18f",
      "status": "current",
      "type": {
        "coding": [ {
          "system": "http://loinc.org",
          "code": "LOINC:39942-8",
          "display": "V/Q scan in pneumonectomy report"
        } ],
        "text": "V/Q scan in pneumonectomy report"
      },
      "subject": {
        "reference": "Patient/5f6bfd47-49c2-4423-a38b-5731af7d94cb"
      },
      "content": [ {
        "attachment": {
          "contentType": "application/pdf",
          "data": "bHVuZ3Zx",
          "title": "V/Q scan in pneumonectomy report"
        }
      } ]
    }
  }, {
    "fullUrl": "DiagnosticReport/9f140b11-f514-46eb-87f7-e4678510e865",
    "resource": {
      "resourceType": "DiagnosticReport",
      "id": "9f140b11-f514-46eb-87f7-e4678510e865",
      "status": "final",
      "code": {
        "coding": [ {
          "system": "http://loinc.org",
          "code": "LOINC:64098-7",
          "display": "6MWT"
        } ],
        "text": "6MWT"
      },
      "subject": {
        "reference": "Patient/5f6bfd47-49c2-4423-a38b-5731af7d94cb",
        "display": "Testing POC"
      },
      "issued": "2024-05-31T22:10:13.060+05:30",
      "result": [ {
        "reference": "DocumentReference/0cd987be-277d-4c9d-a3fe-ae865f9e4963"
      } ]
    }
  }, {
    "fullUrl": "DocumentReference/0cd987be-277d-4c9d-a3fe-ae865f9e4963",
    "resource": {
      "resourceType": "DocumentReference",
      "id": "0cd987be-277d-4c9d-a3fe-ae865f9e4963",
      "status": "current",
      "type": {
        "coding": [ {
          "system": "http://loinc.org",
          "code": "LOINC:64098-7",
          "display": "6MWT report"
        } ],
        "text": "6MWT report"
      },
      "subject": {
        "reference": "Patient/5f6bfd47-49c2-4423-a38b-5731af7d94cb"
      },
      "content": [ {
        "attachment": {
          "contentType": "application/pdf",
          "data": "bHVuZzZtd3Q=",
          "title": "6MWT report"
        }
      } ]
    }
  }, {
    "fullUrl": "DiagnosticReport/fd16f2ed-8f54-4684-a2c7-5090267770ca",
    "resource": {
      "resourceType": "DiagnosticReport",
      "id": "fd16f2ed-8f54-4684-a2c7-5090267770ca",
      "status": "final",
      "code": {
        "coding": [ {
          "system": "http://loinc.org",
          "code": "LOINC:73977-1",
          "display": "Molecular markers/NGS as needed"
        } ],
        "text": "Molecular markers/NGS as needed"
      },
      "subject": {
        "reference": "Patient/5f6bfd47-49c2-4423-a38b-5731af7d94cb",
        "display": "Testing POC"
      },
      "issued": "2024-05-31T22:10:13.060+05:30",
      "result": [ {
        "reference": "DocumentReference/4c65bb06-58de-4562-9825-ad304fba3a79"
      } ]
    }
  }, {
    "fullUrl": "DocumentReference/4c65bb06-58de-4562-9825-ad304fba3a79",
    "resource": {
      "resourceType": "DocumentReference",
      "id": "4c65bb06-58de-4562-9825-ad304fba3a79",
      "status": "current",
      "type": {
        "coding": [ {
          "system": "http://loinc.org",
          "code": "LOINC:73977-1",
          "display": "Molecular markers/NGS as needed report"
        } ],
        "text": "Molecular markers/NGS as needed report"
      },
      "subject": {
        "reference": "Patient/5f6bfd47-49c2-4423-a38b-5731af7d94cb"
      },
      "content": [ {
        "attachment": {
          "contentType": "application/pdf",
          "data": "bHVuZ01vbGVjdWxhciBtYXJrZXJzL05HUyBhcyBuZWVkZWQ=",
          "title": "Molecular markers/NGS as needed report"
        }
      } ]
    }
  }, {
    "fullUrl": "Condition/114c216b-b5f3-4a71-a7d2-43a7b91017d1",
    "resource": {
      "resourceType": "Condition",
      "id": "114c216b-b5f3-4a71-a7d2-43a7b91017d1",
      "meta": {
        "versionId": "0",
        "lastUpdated": "2024-05-31T22:10:13.061+05:30",
        "profile": [ "https://nrces.in/ndhm/fhir/r4/StructureDefinition/Condition" ]
      },
      "clinicalStatus": {
        "coding": [ {
          "system": "http://terminology.hl7.org/CodeSystem/condition-clinical",
          "code": "active",
          "display": "active"
        } ],
        "text": "Active"
      },
      "code": {
        "coding": [ {
          "system": "http://loinc.org",
          "code": "LOINC:54014-2",
          "display": "Oral Cancer"
        } ],
        "text": "Oral Cancer"
      }
    }
  }, {
    "fullUrl": "DiagnosticReport/d06004fa-cd8e-47b9-ae67-da4f15bcce18",
    "resource": {
      "resourceType": "DiagnosticReport",
      "id": "d06004fa-cd8e-47b9-ae67-da4f15bcce18",
      "status": "final",
      "code": {
        "coding": [ {
          "system": "http://loinc.org",
          "code": "LOINC:87179-8",
          "display": "FNAC report"
        } ],
        "text": "FNAC report"
      },
      "subject": {
        "reference": "Patient/5f6bfd47-49c2-4423-a38b-5731af7d94cb"
      },
      "issued": "2024-05-31T22:10:13.061+05:30",
      "result": [ {
        "reference": "DocumentReference/e802de85-8b42-405e-a7cf-4ac3b9706a80"
      } ]
    }
  }, {
    "fullUrl": "DocumentReference/e802de85-8b42-405e-a7cf-4ac3b9706a80",
    "resource": {
      "resourceType": "DocumentReference",
      "id": "e802de85-8b42-405e-a7cf-4ac3b9706a80",
      "status": "current",
      "type": {
        "coding": [ {
          "system": "http://loinc.org",
          "code": "LOINC:87179-8",
          "display": "FNAC report report"
        } ],
        "text": "FNAC report report"
      },
      "subject": {
        "reference": "Patient/5f6bfd47-49c2-4423-a38b-5731af7d94cb"
      },
      "content": [ {
        "attachment": {
          "contentType": "application/pdf",
          "data": "b3JhbGd2cQ==",
          "title": "FNAC report report"
        }
      } ]
    }
  }, {
    "fullUrl": "DiagnosticReport/e1e1bd99-b622-44c2-8045-a6b728cca7f9",
    "resource": {
      "resourceType": "DiagnosticReport",
      "id": "e1e1bd99-b622-44c2-8045-a6b728cca7f9",
      "status": "final",
      "code": {
        "coding": [ {
          "system": "http://loinc.org",
          "code": "LOINC:24627-2",
          "display": "CECT head neck thorax report/ PET Ct/ MRI"
        } ],
        "text": "CECT head neck thorax report/ PET Ct/ MRI"
      },
      "subject": {
        "reference": "Patient/5f6bfd47-49c2-4423-a38b-5731af7d94cb",
        "display": "Testing POC"
      },
      "issued": "2024-05-31T22:10:13.061+05:30",
      "result": [ {
        "reference": "DocumentReference/16866073-f2fc-426e-9c47-856991debc2a"
      } ]
    }
  }, {
    "fullUrl": "DocumentReference/16866073-f2fc-426e-9c47-856991debc2a",
    "resource": {
      "resourceType": "DocumentReference",
      "id": "16866073-f2fc-426e-9c47-856991debc2a",
      "status": "current",
      "type": {
        "coding": [ {
          "system": "http://loinc.org",
          "code": "LOINC:24627-2",
          "display": "CECT head neck thorax report/ PET Ct/ MRI report"
        } ],
        "text": "CECT head neck thorax report/ PET Ct/ MRI report"
      },
      "subject": {
        "reference": "Patient/5f6bfd47-49c2-4423-a38b-5731af7d94cb"
      },
      "content": [ {
        "attachment": {
          "contentType": "application/pdf",
          "data": "b3JhbDZtd3Q=",
          "title": "CECT head neck thorax report/ PET Ct/ MRI report"
        }
      } ]
    }
  }, {
    "fullUrl": "AllergyIntolerance/02d5b560-390c-4003-9567-a187d13cc843",
    "resource": {
      "resourceType": "AllergyIntolerance",
      "id": "02d5b560-390c-4003-9567-a187d13cc843",
      "meta": {
        "profile": [ "https://nrces.in/ndhm/fhir/r4/StructureDefinition/AllergyIntolerance" ]
      },
      "text": {
        "status": "generated",
        "div": "<div xmlns=\"http://www.w3.org/1999/xhtml\"><p>groundnut</p><p>recordedDate:2015-08-06</p></div>"
      },
      "clinicalStatus": {
        "coding": [ {
          "system": "http://terminology.hl7.org/CodeSystem/allergyintolerance-clinical",
          "code": "active",
          "display": "Active"
        } ],
        "text": "Active"
      },
      "verificationStatus": {
        "coding": [ {
          "system": "http://terminology.hl7.org/CodeSystem/allergyintolerance-verification",
          "code": "confirmed",
          "display": "Confirmed"
        } ],
        "text": "Confirmed"
      },
      "code": {
        "coding": [ {
          "system": "http://snomed.info/sct",
          "code": "235719002",
          "display": "groundnut"
        } ],
        "text": "groundnut"
      },
      "patient": {
        "reference": "Patient/5f6bfd47-49c2-4423-a38b-5731af7d94cb"
      },
      "recordedDate": "2024-05-31T22:10:13+05:30",
      "recorder": {
        "reference": "409c7931-4ecd-406c-b698-9f39128b536e"
      },
      "note": [ {
        "text": "The patient reports of: groundnut allergy which is of type: food"
      } ]
    }
  }, {
    "fullUrl": "AllergyIntolerance/af144939-01d7-4f1c-a41b-d3e3b262fd6f",
    "resource": {
      "resourceType": "AllergyIntolerance",
      "id": "af144939-01d7-4f1c-a41b-d3e3b262fd6f",
      "meta": {
        "profile": [ "https://nrces.in/ndhm/fhir/r4/StructureDefinition/AllergyIntolerance" ]
      },
      "text": {
        "status": "generated",
        "div": "<div xmlns=\"http://www.w3.org/1999/xhtml\"><p>dust</p><p>recordedDate:2015-08-06</p></div>"
      },
      "clinicalStatus": {
        "coding": [ {
          "system": "http://terminology.hl7.org/CodeSystem/allergyintolerance-clinical",
          "code": "active",
          "display": "Active"
        } ],
        "text": "Active"
      },
      "verificationStatus": {
        "coding": [ {
          "system": "http://terminology.hl7.org/CodeSystem/allergyintolerance-verification",
          "code": "confirmed",
          "display": "Confirmed"
        } ],
        "text": "Confirmed"
      },
      "code": {
        "coding": [ {
          "system": "http://snomed.info/sct",
          "code": "235719002",
          "display": "dust"
        } ],
        "text": "dust"
      },
      "patient": {
        "reference": "Patient/5f6bfd47-49c2-4423-a38b-5731af7d94cb"
      },
      "recordedDate": "2024-05-31T22:10:13+05:30",
      "recorder": {
        "reference": "816829bb-5f73-4570-a4d2-0778c211199b"
      },
      "note": [ {
        "text": "The patient reports of: dust allergy which is of type: environmental"
      } ]
    }
  }, {
    "fullUrl": "Condition/ee2ac5a0-7486-45b4-b81d-4eadc083fde3",
    "resource": {
      "resourceType": "Condition",
      "id": "ee2ac5a0-7486-45b4-b81d-4eadc083fde3",
      "meta": {
        "versionId": "0",
        "lastUpdated": "2024-05-31T22:10:13.065+05:30",
        "profile": [ "https://nrces.in/ndhm/fhir/r4/StructureDefinition/Condition" ]
      },
      "text": {
        "status": "generated",
        "div": "<div xmlns=\"http://www.w3.org/1999/xhtml\"><p><b>Generated Narrative: Condition</b><a name=\"example-02\"> </a></p><div style=\"display: inline-block; background-color: #d9e0e7; padding: 6px; margin: 4px; border: 1px solid #8da1b4; border-radius: 5px; line-height: 60%\"><p style=\"margin-bottom: 0px\">Resource Condition &quot;example-02&quot; </p><p style=\"margin-bottom: 0px\">Profile: <a href=\"StructureDefinition-Condition.html\">Condition</a></p></div><p><b>code</b>: Type 2 diabetes mellitus <span style=\"background: LightGoldenRodYellow; margin: 4px; border: 1px solid khaki\"> (<a href=\"https://browser.ihtsdotools.org/\">SNOMED CT</a>#44054006)</span></p><p><b>subject</b>: <a href=\"Patient-example-01.html\">Patient/example-01</a> &quot;&quot;</p><p><b>recorder</b>: <a href=\"Practitioner-example-01.html\">Practitioner/example-01</a> &quot;&quot;</p></div>"
      },
      "verificationStatus": {
        "coding": [ {
          "system": "http://terminology.hl7.org/CodeSystem/condition-ver-status",
          "code": "confirmed",
          "display": "Confirmed"
        } ]
      },
      "category": [ {
        "coding": [ {
          "system": "http://snomed.info/sct",
          "code": "11493005",
          "display": "Problem List Item"
        } ]
      } ],
      "code": {
        "coding": [ {
          "system": "http://snomed.info/sct",
          "code": "38341003",
          "display": "hypertension"
        } ]
      },
      "subject": {
        "reference": "Patient/5f6bfd47-49c2-4423-a38b-5731af7d94cb"
      },
      "recorder": {
        "reference": "Practitioner/50901e45-1580-414b-b127-5e69ce69e30d"
      }
    }
  }, {
    "fullUrl": "Condition/0f58b677-6825-4835-91a3-8dfe04b3d4c4",
    "resource": {
      "resourceType": "Condition",
      "id": "0f58b677-6825-4835-91a3-8dfe04b3d4c4",
      "meta": {
        "versionId": "0",
        "lastUpdated": "2024-05-31T22:10:13.065+05:30",
        "profile": [ "https://nrces.in/ndhm/fhir/r4/StructureDefinition/Condition" ]
      },
      "text": {
        "status": "generated",
        "div": "<div xmlns=\"http://www.w3.org/1999/xhtml\"><p><b>Generated Narrative: Condition</b><a name=\"example-02\"> </a></p><div style=\"display: inline-block; background-color: #d9e0e7; padding: 6px; margin: 4px; border: 1px solid #8da1b4; border-radius: 5px; line-height: 60%\"><p style=\"margin-bottom: 0px\">Resource Condition &quot;example-02&quot; </p><p style=\"margin-bottom: 0px\">Profile: <a href=\"StructureDefinition-Condition.html\">Condition</a></p></div><p><b>code</b>: Type 2 diabetes mellitus <span style=\"background: LightGoldenRodYellow; margin: 4px; border: 1px solid khaki\"> (<a href=\"https://browser.ihtsdotools.org/\">SNOMED CT</a>#44054006)</span></p><p><b>subject</b>: <a href=\"Patient-example-01.html\">Patient/example-01</a> &quot;&quot;</p><p><b>recorder</b>: <a href=\"Practitioner-example-01.html\">Practitioner/example-01</a> &quot;&quot;</p></div>"
      },
      "verificationStatus": {
        "coding": [ {
          "system": "http://terminology.hl7.org/CodeSystem/condition-ver-status",
          "code": "confirmed",
          "display": "Confirmed"
        } ]
      },
      "category": [ {
        "coding": [ {
          "system": "http://snomed.info/sct",
          "code": "191415000",
          "display": "Encounter Diagnosis"
        } ]
      } ],
      "code": {
        "coding": [ {
          "system": "http://snomed.info/sct",
          "code": "53741008",
          "display": "Coronary Artery Disease"
        } ]
      },
      "subject": {
        "reference": "Patient/5f6bfd47-49c2-4423-a38b-5731af7d94cb"
      },
      "recorder": {
        "reference": "Practitioner/79c1353e-a25b-4c13-a52a-c8d442996a79"
      }
    }
  }, {
    "fullUrl": "AdverseEvent/03f38c75-8b22-4348-bae3-abedebf41c9d",
    "resource": {
      "resourceType": "AdverseEvent",
      "id": "03f38c75-8b22-4348-bae3-abedebf41c9d",
      "identifier": {
        "system": "http://example.com/adverseEvent",
        "value": "123456"
      },
      "actuality": "actual",
      "category": [ {
        "coding": [ {
          "system": "http://snomed.info/sct",
          "code": "407716003",
          "display": "medication-mishap"
        } ],
        "text": "Medication Mishap"
      } ],
      "subject": {
        "reference": "Patient/5f6bfd47-49c2-4423-a38b-5731af7d94cb"
      },
      "date": "2024-05-31T22:10:13+05:30",
      "detected": "2024-05-31T22:10:13+05:30",
      "recordedDate": "2024-05-31T22:10:13+05:30",
      "seriousness": {
        "coding": [ {
          "system": "http://terminology.hl7.org/CodeSystem/adverse-event-seriousness",
          "code": "255604002",
          "display": "serious"
        } ],
        "text": "Serious"
      },
      "outcome": {
        "coding": [ {
          "system": "http://terminology.hl7.org/CodeSystem/adverse-event-outcome",
          "code": "resolved",
          "display": "Resolved"
        } ],
        "text": "Resolved"
      },
      "recorder": {
        "reference": "Practitioner/8317369c-47ee-40cd-9c92-d9da61c63ab9"
      }
    }
  }, {
    "fullUrl": "Condition/ad1c7d3a-c960-4128-9995-d12ca53da231",
    "resource": {
      "resourceType": "Condition",
      "id": "ad1c7d3a-c960-4128-9995-d12ca53da231",
      "meta": {
        "versionId": "0",
        "lastUpdated": "2024-05-31T22:10:13.066+05:30",
        "profile": [ "https://nrces.in/ndhm/fhir/r4/StructureDefinition/Condition" ]
      },
      "text": {
        "status": "generated",
        "div": "<div xmlns=\"http://www.w3.org/1999/xhtml\"><p><b>Narrative with Details</b></p><p><b>id</b>: finding-example-01</p><p><b>status</b>: final</p><p><b>code</b>: Respiratory rate <span>(Details : SNOMED CT code '780834008' = 'Respiratory rate normal', given as 'Respiratory rate normal')</span></p><p><b>subject</b>: ABC</p><p><b>performer</b>: Dr. DEF, MD</p><p><b>value</b>: 18 breaths/minute<span> (Details: UCUM code /min = '/min')</span></p><h3>ReferenceRanges</h3><table><tr><td>-</td><td><b>Low</b></td></tr><tr><td>*</td><td>12 breaths/minute<span> (Details: UCUM code /min = '/min')</span></td></tr><tr><td>-</td><td><b>High</b></td></tr><tr><td>*</td><td>20 breaths/minute<span> (Details: UCUM code /min = '/min')</span></td></tr></table></div>"
      },
      "clinicalStatus": {
        "coding": [ {
          "system": "http://terminology.hl7.org/CodeSystem/condition-clinical",
          "code": "resolved",
          "display": "Resolved"
        } ]
      },
      "verificationStatus": {
        "coding": [ {
          "system": "http://terminology.hl7.org/CodeSystem/condition-ver-status",
          "code": "confirmed",
          "display": "Confirmed"
        } ]
      },
      "code": {
        "coding": [ {
          "system": "http://snomed.info/sct",
          "code": "38341003",
          "display": "hypertension"
        } ]
      },
      "subject": {
        "reference": "Patient/5f6bfd47-49c2-4423-a38b-5731af7d94cb"
      },
      "recordedDate": "2024-05-31T22:10:13+05:30"
    }
  }, {
    "fullUrl": "Condition/58ea0dc5-b0aa-4195-8376-8cc6c7339617",
    "resource": {
      "resourceType": "Condition",
      "id": "58ea0dc5-b0aa-4195-8376-8cc6c7339617",
      "meta": {
        "versionId": "0",
        "lastUpdated": "2024-05-31T22:10:13.067+05:30",
        "profile": [ "https://nrces.in/ndhm/fhir/r4/StructureDefinition/Condition" ]
      },
      "text": {
        "status": "generated",
        "div": "<div xmlns=\"http://www.w3.org/1999/xhtml\"><p><b>Narrative with Details</b></p><p><b>id</b>: finding-example-01</p><p><b>status</b>: final</p><p><b>code</b>: Respiratory rate <span>(Details : SNOMED CT code '780834008' = 'Respiratory rate normal', given as 'Respiratory rate normal')</span></p><p><b>subject</b>: ABC</p><p><b>performer</b>: Dr. DEF, MD</p><p><b>value</b>: 18 breaths/minute<span> (Details: UCUM code /min = '/min')</span></p><h3>ReferenceRanges</h3><table><tr><td>-</td><td><b>Low</b></td></tr><tr><td>*</td><td>12 breaths/minute<span> (Details: UCUM code /min = '/min')</span></td></tr><tr><td>-</td><td><b>High</b></td></tr><tr><td>*</td><td>20 breaths/minute<span> (Details: UCUM code /min = '/min')</span></td></tr></table></div>"
      },
      "clinicalStatus": {
        "coding": [ {
          "system": "http://terminology.hl7.org/CodeSystem/condition-clinical",
          "code": "resolved",
          "display": "Resolved"
        } ]
      },
      "verificationStatus": {
        "coding": [ {
          "system": "http://terminology.hl7.org/CodeSystem/condition-ver-status",
          "code": "confirmed",
          "display": "Confirmed"
        } ]
      },
      "code": {
        "coding": [ {
          "system": "http://snomed.info/sct",
          "code": "53741008",
          "display": "Coronary Artery Disease"
        } ]
      },
      "subject": {
        "reference": "Patient/5f6bfd47-49c2-4423-a38b-5731af7d94cb"
      },
      "recordedDate": "2024-05-31T22:10:13+05:30"
    }
  }, {
    "fullUrl": "Condition/7e349876-9ed3-4b80-a492-3f5ea60d18ff",
    "resource": {
      "resourceType": "Condition",
      "id": "7e349876-9ed3-4b80-a492-3f5ea60d18ff",
      "meta": {
        "versionId": "0",
        "lastUpdated": "2024-05-31T22:10:13.067+05:30",
        "profile": [ "https://nrces.in/ndhm/fhir/r4/StructureDefinition/Condition" ]
      },
      "text": {
        "status": "generated",
        "div": "<div xmlns=\"http://www.w3.org/1999/xhtml\"><p><b>Narrative with Details</b></p><p><b>id</b>: finding-example-01</p><p><b>status</b>: final</p><p><b>code</b>: Respiratory rate <span>(Details : SNOMED CT code '780834008' = 'Respiratory rate normal', given as 'Respiratory rate normal')</span></p><p><b>subject</b>: ABC</p><p><b>performer</b>: Dr. DEF, MD</p><p><b>value</b>: 18 breaths/minute<span> (Details: UCUM code /min = '/min')</span></p><h3>ReferenceRanges</h3><table><tr><td>-</td><td><b>Low</b></td></tr><tr><td>*</td><td>12 breaths/minute<span> (Details: UCUM code /min = '/min')</span></td></tr><tr><td>-</td><td><b>High</b></td></tr><tr><td>*</td><td>20 breaths/minute<span> (Details: UCUM code /min = '/min')</span></td></tr></table></div>"
      },
      "clinicalStatus": {
        "coding": [ {
          "system": "http://terminology.hl7.org/CodeSystem/condition-clinical",
          "code": "resolved",
          "display": "Resolved"
        } ]
      },
      "verificationStatus": {
        "coding": [ {
          "system": "http://terminology.hl7.org/CodeSystem/condition-ver-status",
          "code": "confirmed",
          "display": "Confirmed"
        } ]
      },
      "code": {
        "coding": [ {
          "system": "http://snomed.info/sct",
          "code": "38341003",
          "display": "hypertension"
        } ]
      },
      "subject": {
        "reference": "Patient/5f6bfd47-49c2-4423-a38b-5731af7d94cb"
      },
      "recordedDate": "2024-05-31T22:10:13+05:30"
    }
  }, {
    "fullUrl": "Condition/25488d23-801a-452c-92e6-3952c2daef55",
    "resource": {
      "resourceType": "Condition",
      "id": "25488d23-801a-452c-92e6-3952c2daef55",
      "meta": {
        "versionId": "0",
        "lastUpdated": "2024-05-31T22:10:13.068+05:30",
        "profile": [ "https://nrces.in/ndhm/fhir/r4/StructureDefinition/Condition" ]
      },
      "text": {
        "status": "generated",
        "div": "<div xmlns=\"http://www.w3.org/1999/xhtml\"><p><b>Narrative with Details</b></p><p><b>id</b>: finding-example-01</p><p><b>status</b>: final</p><p><b>code</b>: Respiratory rate <span>(Details : SNOMED CT code '780834008' = 'Respiratory rate normal', given as 'Respiratory rate normal')</span></p><p><b>subject</b>: ABC</p><p><b>performer</b>: Dr. DEF, MD</p><p><b>value</b>: 18 breaths/minute<span> (Details: UCUM code /min = '/min')</span></p><h3>ReferenceRanges</h3><table><tr><td>-</td><td><b>Low</b></td></tr><tr><td>*</td><td>12 breaths/minute<span> (Details: UCUM code /min = '/min')</span></td></tr><tr><td>-</td><td><b>High</b></td></tr><tr><td>*</td><td>20 breaths/minute<span> (Details: UCUM code /min = '/min')</span></td></tr></table></div>"
      },
      "clinicalStatus": {
        "coding": [ {
          "system": "http://terminology.hl7.org/CodeSystem/condition-clinical",
          "code": "resolved",
          "display": "Resolved"
        } ]
      },
      "verificationStatus": {
        "coding": [ {
          "system": "http://terminology.hl7.org/CodeSystem/condition-ver-status",
          "code": "confirmed",
          "display": "Confirmed"
        } ]
      },
      "code": {
        "coding": [ {
          "system": "http://snomed.info/sct",
          "code": "53741008",
          "display": "Coronary Artery Disease"
        } ]
      },
      "subject": {
        "reference": "Patient/5f6bfd47-49c2-4423-a38b-5731af7d94cb"
      },
      "recordedDate": "2024-05-31T22:10:13+05:30"
    }
  }, {
    "fullUrl": "Observation/0f442276-e2d7-40ba-aa68-a50403a32f80",
    "resource": {
      "resourceType": "Observation",
      "id": "0f442276-e2d7-40ba-aa68-a50403a32f80",
      "meta": {
        "versionId": "0",
        "lastUpdated": "2024-05-31T22:10:13.068+05:30",
        "profile": [ "https://nrces.in/ndhm/fhir/r4/StructureDefinition/Observation" ]
      },
      "text": {
        "status": "generated",
        "div": "<div xmlns=\"http://www.w3.org/1999/xhtml\"><p><b>Narrative with Details</b></p><p><b>id</b>: example-20</p><p><b>status</b>: final</p><p><b>code</b>: Age at menarche <span>(Details : LOINC code '42798-9' = 'Age at menarche', given as 'Age at menarche')</span></p><p><b>subject</b>: ABC</p><p><b>value</b>: 14 age</p></div>"
      },
      "status": "final",
      "code": {
        "coding": [ {
          "system": "http://loinc.org",
          "code": "82810-3",
          "display": "Pregnancy status"
        } ],
        "text": "Pregnancy status"
      },
      "subject": {
        "reference": "Patient/5f6bfd47-49c2-4423-a38b-5731af7d94cb"
      },
      "effectiveDateTime": "2024-05-31T22:10:13+05:30",
      "performer": [ {
        "reference": "Practitioner/b396a96b-ad30-451b-a5bc-7cfb0b4e3fbc"
      } ],
      "valueString": "Not pregnant"
    }
  }, {
    "fullUrl": "Observation/a6b864da-e41d-45f1-b9a2-b910e521676b",
    "resource": {
      "resourceType": "Observation",
      "id": "a6b864da-e41d-45f1-b9a2-b910e521676b",
      "meta": {
        "versionId": "0",
        "lastUpdated": "2024-05-31T22:10:13.069+05:30",
        "profile": [ "https://nrces.in/ndhm/fhir/r4/StructureDefinition/Observation" ]
      },
      "text": {
        "status": "generated",
        "div": "<div xmlns=\"http://www.w3.org/1999/xhtml\"><p><b>Narrative with Details</b></p><p><b>id</b>: example-20</p><p><b>status</b>: final</p><p><b>code</b>: Age at menarche <span>(Details : LOINC code '42798-9' = 'Age at menarche', given as 'Age at menarche')</span></p><p><b>subject</b>: ABC</p><p><b>value</b>: 14 age</p></div>"
      },
      "status": "final",
      "code": {
        "coding": [ {
          "system": "http://loinc.org",
          "code": "83318-7",
          "display": "Menstrual cycle"
        } ],
        "text": "Menstrual cycle"
      },
      "subject": {
        "reference": "Patient/5f6bfd47-49c2-4423-a38b-5731af7d94cb"
      },
      "effectiveDateTime": "2024-05-31T22:10:13+05:30",
      "performer": [ {
        "reference": "Practitioner/5c2bf4c2-79a6-4211-8631-d17adfb44ba3"
      } ],
      "valueString": "Regular"
    }
  }, {
    "fullUrl": "Observation/cf93b34d-a34d-44b1-8c88-4ab2c0c1c6dd",
    "resource": {
      "resourceType": "Observation",
      "id": "cf93b34d-a34d-44b1-8c88-4ab2c0c1c6dd",
      "meta": {
        "versionId": "0",
        "lastUpdated": "2024-05-31T22:10:13.069+05:30",
        "profile": [ "https://nrces.in/ndhm/fhir/r4/StructureDefinition/ObservationWomenHealth" ]
      },
      "text": {
        "status": "generated",
        "div": "<div xmlns=\"http://www.w3.org/1999/xhtml\"><p><b>Narrative with Details</b></p><p><b>id</b>: example-20</p><p><b>status</b>: final</p><p><b>code</b>: Age at menarche <span>(Details : LOINC code '42798-9' = 'Age at menarche', given as 'Age at menarche')</span></p><p><b>subject</b>: ABC</p><p><b>value</b>: 14 age</p></div>"
      },
      "status": "final",
      "code": {
        "coding": [ {
          "system": "http://loinc.org",
          "code": "82810-3",
          "display": "Pregnancy status"
        } ],
        "text": "Pregnancy status"
      },
      "subject": {
        "reference": "Patient/5f6bfd47-49c2-4423-a38b-5731af7d94cb"
      },
      "effectiveDateTime": "2024-05-31T22:10:13+05:30",
      "performer": [ {
        "reference": "Practitioner/6f1f23e7-c61b-4004-9caf-874b1da9c915"
      } ],
      "valueString": "Not pregnant"
    }
  }, {
    "fullUrl": "Observation/76e065d1-4942-43f3-825d-b2779d2e1880",
    "resource": {
      "resourceType": "Observation",
      "id": "76e065d1-4942-43f3-825d-b2779d2e1880",
      "meta": {
        "versionId": "0",
        "lastUpdated": "2024-05-31T22:10:13.070+05:30",
        "profile": [ "https://nrces.in/ndhm/fhir/r4/StructureDefinition/ObservationWomenHealth" ]
      },
      "text": {
        "status": "generated",
        "div": "<div xmlns=\"http://www.w3.org/1999/xhtml\"><p><b>Narrative with Details</b></p><p><b>id</b>: example-20</p><p><b>status</b>: final</p><p><b>code</b>: Age at menarche <span>(Details : LOINC code '42798-9' = 'Age at menarche', given as 'Age at menarche')</span></p><p><b>subject</b>: ABC</p><p><b>value</b>: 14 age</p></div>"
      },
      "status": "final",
      "code": {
        "coding": [ {
          "system": "http://loinc.org",
          "code": "83318-7",
          "display": "Menstrual cycle"
        } ],
        "text": "Menstrual cycle"
      },
      "subject": {
        "reference": "Patient/5f6bfd47-49c2-4423-a38b-5731af7d94cb"
      },
      "effectiveDateTime": "2024-05-31T22:10:13+05:30",
      "performer": [ {
        "reference": "Practitioner/4903ac1f-59af-411a-912f-5a1b1ba212bf"
      } ],
      "valueString": "Regular"
    }
  }, {
    "fullUrl": "ServiceRequest/748d3321-3ca4-4118-ac9f-91436f7406f4",
    "resource": {
      "resourceType": "ServiceRequest",
      "id": "748d3321-3ca4-4118-ac9f-91436f7406f4",
      "status": "active",
      "intent": "original-order",
      "code": {
        "coding": [ {
          "system": "http://loinc.org",
          "code": "10187-3",
          "display": "obstetric history"
        } ],
        "text": "obstetric history"
      },
      "subject": {
        "reference": "Patient/5f6bfd47-49c2-4423-a38b-5731af7d94cb"
      },
      "occurrenceDateTime": "2013-05-08T09:33:27+07:00",
      "requester": {
        "reference": "Practitioner/example1"
      }
    }
  }, {
    "fullUrl": "ServiceRequest/f70b7a52-32f5-4b78-88f9-930da707cc85",
    "resource": {
      "resourceType": "ServiceRequest",
      "id": "f70b7a52-32f5-4b78-88f9-930da707cc85",
      "status": "active",
      "intent": "original-order",
      "code": {
        "coding": [ {
          "system": "http://loinc.org",
          "code": "10193-1",
          "display": "breast health"
        } ],
        "text": "breast health"
      },
      "subject": {
        "reference": "Patient/5f6bfd47-49c2-4423-a38b-5731af7d94cb"
      },
      "occurrenceDateTime": "2015-08-27T09:33:27+07:00",
      "requester": {
        "reference": "Practitioner/example2"
      }
    }
  }, {
    "fullUrl": "Procedure/ff8cfa0d-5922-45aa-b864-14a631ac72b8",
    "resource": {
      "resourceType": "Procedure",
      "id": "ff8cfa0d-5922-45aa-b864-14a631ac72b8",
      "status": "completed",
      "statusReason": {
        "coding": [ {
          "system": "http://snomed.info/sct",
          "code": "125661000119109",
          "display": "device"
        } ],
        "text": "Device"
      },
      "category": {
        "coding": [ {
          "system": "http://snomed.info/sct",
          "code": "125661000119109",
          "display": "device"
        } ],
        "text": "Device"
      },
      "code": {
        "coding": [ {
          "system": "http://snomed.info/sct",
          "code": "125661000119109",
          "display": "device"
        } ],
        "text": "Device"
      },
      "subject": {
        "reference": "Patient/5f6bfd47-49c2-4423-a38b-5731af7d94cb"
      },
      "performedPeriod": {
        "start": "2011-06-26",
        "end": "2011-06-27"
      },
      "reasonCode": [ {
        "coding": [ {
          "system": "http://snomed.info/sct",
          "code": "125661000119109",
          "display": "device"
        } ],
        "text": "Device"
      } ],
      "bodySite": [ {
        "coding": [ {
          "system": "http://snomed.info/sct",
          "code": "125661000119109",
          "display": "device"
        } ],
        "text": "Device"
      } ],
      "outcome": {
        "text": "improved blood circulation"
      },
      "followUp": [ {
        "text": "described in care plan"
      } ],
      "usedCode": [ {
        "text": "device"
      } ]
    }
  }, {
    "fullUrl": "Procedure/376f0c08-049a-4330-a248-eac0f5fe484c",
    "resource": {
      "resourceType": "Procedure",
      "id": "376f0c08-049a-4330-a248-eac0f5fe484c",
      "status": "completed",
      "statusReason": {
        "coding": [ {
          "system": "http://snomed.info/sct",
          "code": "386368001",
          "display": "wrong-patient"
        } ],
        "text": "Wrong Patient"
      },
      "category": {
        "coding": [ {
          "system": "http://snomed.info/sct",
          "code": "386368001",
          "display": "wrong-patient"
        } ],
        "text": "Wrong Patient"
      },
      "code": {
        "coding": [ {
          "system": "http://snomed.info/sct",
          "code": "386368001",
          "display": "wrong-patient"
        } ],
        "text": "Wrong Patient"
      },
      "subject": {
        "reference": "Patient/5f6bfd47-49c2-4423-a38b-5731af7d94cb"
      },
      "performedPeriod": {
        "start": "2013-01-28T13:31:00+01:00",
        "end": "2013-01-28T14:27:00+01:00"
      },
      "reasonCode": [ {
        "coding": [ {
          "system": "http://snomed.info/sct",
          "code": "386368001",
          "display": "wrong-patient"
        } ],
        "text": "Wrong Patient"
      } ],
      "bodySite": [ {
        "coding": [ {
          "system": "http://snomed.info/sct",
          "code": "386368001",
          "display": "wrong-patient"
        } ],
        "text": "Wrong Patient"
      } ],
      "outcome": {
        "text": "improved blood circulation"
      },
      "followUp": [ {
        "text": "described in care plan"
      } ],
      "usedCode": [ {
        "text": "wrong-patient"
      } ]
    }
  }, {
    "fullUrl": "MedicationStatement/ca0a2345-89f8-4688-af43-f3bb4e485907",
    "resource": {
      "resourceType": "MedicationStatement",
      "id": "ca0a2345-89f8-4688-af43-f3bb4e485907",
      "status": "completed",
      "medicationCodeableConcept": {
        "coding": [ {
          "system": "http://snomed.info/sct",
          "code": "125661000119109",
          "display": "device"
        } ],
        "text": "Device"
      },
      "subject": {
        "reference": "Patient/5f6bfd47-49c2-4423-a38b-5731af7d94cb"
      },
      "effectivePeriod": {
        "start": "2014-02-01T05:30:00+05:30"
      },
      "dateAsserted": "2014-02-22T05:30:00+05:30",
      "derivedFrom": [ {
        "reference": "Patient/pat1"
      } ],
      "reasonCode": [ {
        "coding": [ {
          "system": "http://snomed.info/sct",
          "code": "125661000119109",
          "display": "device"
        } ],
        "text": "Device"
      } ],
      "note": [ {
        "text": "Father indicates they miss the occasional dose"
      } ],
      "dosage": [ {
        "additionalInstruction": [ {
          "coding": [ {
            "system": "http://snomed.info/sct",
            "code": "125661000119109",
            "display": "device"
          } ],
          "text": "Device"
        } ],
        "site": {
          "coding": [ {
            "system": "http://snomed.info/sct",
            "code": "125661000119109",
            "display": "device"
          } ],
          "text": "Device"
        },
        "route": {
          "coding": [ {
            "system": "http://snomed.info/sct",
            "code": "125661000119109",
            "display": "device"
          } ],
          "text": "Device"
        },
        "method": {
          "coding": [ {
            "system": "http://snomed.info/sct",
            "code": "125661000119109",
            "display": "device"
          } ],
          "text": "Device"
        },
        "doseAndRate": [ {
          "doseQuantity": {
            "value": 500,
            "unit": "mg",
            "system": "http://unitsofmeasure.org",
            "code": "mg"
          },
          "rateQuantity": {
            "value": 3,
            "unit": "times per day",
            "system": "http://unitsofmeasure.org",
            "code": "times/day"
          }
        } ]
      } ]
    }
  }, {
    "fullUrl": "MedicationStatement/8c797e26-705a-4e55-8394-58dbb59cef7c",
    "resource": {
      "resourceType": "MedicationStatement",
      "id": "8c797e26-705a-4e55-8394-58dbb59cef7c",
      "status": "completed",
      "medicationCodeableConcept": {
        "coding": [ {
          "system": "http://snomed.info/sct",
          "code": "386368001",
          "display": "wrong-patient"
        } ],
        "text": "Wrong Patient"
      },
      "subject": {
        "reference": "Patient/5f6bfd47-49c2-4423-a38b-5731af7d94cb"
      },
      "effectivePeriod": {
        "start": "2015-01-23T05:30:00+05:30"
      },
      "dateAsserted": "2015-02-22T05:30:00+05:30",
      "derivedFrom": [ {
        "reference": "MedicationRequest/medrx002"
      } ],
      "reasonCode": [ {
        "coding": [ {
          "system": "http://snomed.info/sct",
          "code": "386368001",
          "display": "wrong-patient"
        } ],
        "text": "Wrong Patient"
      } ],
      "note": [ {
        "text": "Patient indicates they miss the occasional dose"
      } ],
      "dosage": [ {
        "additionalInstruction": [ {
          "coding": [ {
            "system": "http://snomed.info/sct",
            "code": "386368001",
            "display": "wrong-patient"
          } ],
          "text": "Wrong Patient"
        } ],
        "site": {
          "coding": [ {
            "system": "http://snomed.info/sct",
            "code": "386368001",
            "display": "wrong-patient"
          } ],
          "text": "Wrong Patient"
        },
        "route": {
          "coding": [ {
            "system": "http://snomed.info/sct",
            "code": "386368001",
            "display": "wrong-patient"
          } ],
          "text": "Wrong Patient"
        },
        "method": {
          "coding": [ {
            "system": "http://snomed.info/sct",
            "code": "386368001",
            "display": "wrong-patient"
          } ],
          "text": "Wrong Patient"
        },
        "doseAndRate": [ {
          "doseQuantity": {
            "value": 500,
            "unit": "mg",
            "system": "http://unitsofmeasure.org",
            "code": "mg"
          },
          "rateQuantity": {
            "value": 3,
            "unit": "times per day",
            "system": "http://unitsofmeasure.org",
            "code": "times/day"
          }
        } ]
      } ]
    }
  } ]
}